stegovault/__init__.py
stegovault/archive.py
stegovault/capacity.py
stegovault/cli.py
stegovault/cli_main.py
stegovault/config.py
stegovault/core.py
stegovault/crypto.py
stegovault/errors.py
stegovault/metadata.py
stegovault/robustness.py
stegovault/steganalysis.py
stegovault/ui/gui/__init__.py
stegovault/ui/gui/main_window.py
stegovault/ui/web/__init__.py
stegovault/ui/web/app.py
stegovault-2.0.0.dist-info/licenses/LICENSE
stegovault-2.0.0.dist-info/METADATA
stegovault-2.0.0.dist-info/WHEEL
stegovault-2.0.0.dist-info/entry_points.txt
stegovault-2.0.0.dist-info/top_level.txt
stegovault-2.0.0.dist-info/RECORD
