Metadata-Version: 2.4
Name: stegovault
Version: 2.0.0
Summary: Advanced Steganography & Encryption Toolkit - Hide secrets inside images with military-grade encryption
Home-page: https://github.com/yourusername/StegoVault
Author: StegoVault Contributors
License: MIT
Project-URL: Homepage, https://github.com/yourusername/StegoVault
Project-URL: Documentation, https://github.com/yourusername/StegoVault/blob/main/docs/
Project-URL: Repository, https://github.com/yourusername/StegoVault.git
Project-URL: Issues, https://github.com/yourusername/StegoVault/issues
Project-URL: Changelog, https://github.com/yourusername/StegoVault/releases
Keywords: steganography,encryption,security,privacy,image-processing,cryptography,hiding
Classifier: Development Status :: 4 - Beta
Classifier: Environment :: Console
Classifier: Environment :: Web Environment
Classifier: Intended Audience :: Developers
Classifier: Intended Audience :: Information Technology
Classifier: Intended Audience :: System Administrators
Classifier: License :: OSI Approved :: MIT License
Classifier: Natural Language :: English
Classifier: Operating System :: OS Independent
Classifier: Programming Language :: Python
Classifier: Programming Language :: Python :: 3
Classifier: Programming Language :: Python :: 3.7
Classifier: Programming Language :: Python :: 3.8
Classifier: Programming Language :: Python :: 3.9
Classifier: Programming Language :: Python :: 3.10
Classifier: Programming Language :: Python :: 3.11
Classifier: Programming Language :: Python :: 3.12
Classifier: Topic :: Security
Classifier: Topic :: Security :: Cryptography
Classifier: Topic :: Multimedia :: Graphics
Classifier: Topic :: Multimedia :: Graphics :: Graphics Conversion
Classifier: Topic :: System :: Archiving
Classifier: Topic :: Utilities
Requires-Python: >=3.7
License-File: LICENSE
Requires-Dist: Pillow>=10.0.0
Requires-Dist: numpy>=1.24.0
Requires-Dist: cryptography>=41.0.0
Requires-Dist: tqdm>=4.65.0
Requires-Dist: PyYAML>=6.0
Requires-Dist: colorama>=0.4.6
Provides-Extra: gui
Requires-Dist: PyQt6>=6.5.0; extra == "gui"
Provides-Extra: web
Requires-Dist: Flask>=2.3.0; extra == "web"
Requires-Dist: Werkzeug>=2.3.0; extra == "web"
Provides-Extra: dev
Requires-Dist: pytest>=7.0.0; extra == "dev"
Requires-Dist: black>=23.0.0; extra == "dev"
Requires-Dist: flake8>=6.0.0; extra == "dev"
Requires-Dist: pylance>=1.1.0; extra == "dev"
Provides-Extra: all
Requires-Dist: PyQt6>=6.5.0; extra == "all"
Requires-Dist: Flask>=2.3.0; extra == "all"
Requires-Dist: Werkzeug>=2.3.0; extra == "all"
Requires-Dist: pytest>=7.0.0; extra == "all"
Dynamic: home-page
Dynamic: license-file
Dynamic: requires-python
